bigquery_etl/__init__.py
bigquery_etl/_version.py
bigquery_etl/config.py
bigquery_etl/copy_deduplicate.py
bigquery_etl/dependency.py
bigquery_etl/deploy.py
bigquery_etl/dryrun.py
bigquery_etl/generate_incremental_table.py
bigquery_etl/metrics.py
bigquery_etl/alchemer/__init__.py
bigquery_etl/alchemer/response.schema.json
bigquery_etl/alchemer/survey.py
bigquery_etl/backfill/__init__.py
bigquery_etl/backfill/date_range.py
bigquery_etl/backfill/parse.py
bigquery_etl/backfill/shredder_mitigation.py
bigquery_etl/backfill/shredder_mitigation_checks_template.sql
bigquery_etl/backfill/shredder_mitigation_query_template.sql
bigquery_etl/backfill/utils.py
bigquery_etl/backfill/validate.py
bigquery_etl/braze_currents/__init__.py
bigquery_etl/cli/__init__.py
bigquery_etl/cli/alchemer.py
bigquery_etl/cli/backfill.py
bigquery_etl/cli/check.py
bigquery_etl/cli/dag.py
bigquery_etl/cli/dryrun.py
bigquery_etl/cli/format.py
bigquery_etl/cli/generate.py
bigquery_etl/cli/metadata.py
bigquery_etl/cli/monitoring.py
bigquery_etl/cli/query.py
bigquery_etl/cli/routine.py
bigquery_etl/cli/stage.py
bigquery_etl/cli/static.py
bigquery_etl/cli/utils.py
bigquery_etl/cli/view.py
bigquery_etl/docs/__init__.py
bigquery_etl/docs/bqetl/generate_bqetl_docs.py
bigquery_etl/docs/bqetl/templates/commands.md
bigquery_etl/docs/mozfun/generate_mozfun_docs.py
bigquery_etl/docs/overrides/home.html
bigquery_etl/docs/overrides/main.html
bigquery_etl/dsar/dsar_response.py
bigquery_etl/format_sql/format.py
bigquery_etl/format_sql/formatter.py
bigquery_etl/format_sql/tokenizer.py
bigquery_etl/glam/__init__.py
bigquery_etl/glam/cli.py
bigquery_etl/glam/clients_daily_histogram_aggregates.py
bigquery_etl/glam/clients_daily_scalar_aggregates.py
bigquery_etl/glam/generate.py
bigquery_etl/glam/models.py
bigquery_etl/glam/utils.py
bigquery_etl/glam/templates/clients_daily_histogram_aggregates_v1.sql
bigquery_etl/glam/templates/clients_daily_scalar_aggregates_v1.sql
mozilla_bigquery_etl-2025.1.1.dist-info/LICENSE
mozilla_bigquery_etl-2025.1.1.dist-info/METADATA
mozilla_bigquery_etl-2025.1.1.dist-info/WHEEL
mozilla_bigquery_etl-2025.1.1.dist-info/entry_points.txt
mozilla_bigquery_etl-2025.1.1.dist-info/top_level.txt
mozilla_bigquery_etl-2025.1.1.dist-info/RECORD
