Metadata-Version: 2.2
Name: mozilla-bigquery-etl
Version: 2025.1.1
Summary: Tooling for building derived datasets in BigQuery
Author-email: Mozilla Corporation <fx-data-dev@mozilla.org>
Project-URL: Homepage, https://github.com/mozilla/bigquery-etl
Project-URL: Issues, https://github.com/mozilla/bigquery-etl/issues
Requires-Python: >=3.11
License-File: LICENSE
Requires-Dist: attrs==24.3.0
Requires-Dist: authlib==1.4.0
Requires-Dist: bigeye-sdk==0.4.96
Requires-Dist: black==24.10.0
Requires-Dist: cattrs==24.1.2
Requires-Dist: click==8.1.8
Requires-Dist: cryptography==44.0.0
Requires-Dist: exceptiongroup==1.2.2
Requires-Dist: flake8<5
Requires-Dist: gcsfs==2024.12.0
Requires-Dist: gcloud==0.18.3
Requires-Dist: gitpython==3.1.44
Requires-Dist: google-auth>=2.30.0
Requires-Dist: google-cloud-bigquery==3.27.0
Requires-Dist: google-cloud-bigquery-storage[fastavro]==2.27.0
Requires-Dist: google-cloud-datacatalog-lineage==0.3.11
Requires-Dist: google-cloud-storage==2.19.0
Requires-Dist: Jinja2==3.1.5
Requires-Dist: jsonschema==4.23.0
Requires-Dist: PyJWT==2.10.1
Requires-Dist: markdown-include==0.8.1
Requires-Dist: mdx_truly_sane_lists==1.3
Requires-Dist: mkdocs==1.6.1
Requires-Dist: mkdocs-material==9.5.49
Requires-Dist: mkdocs-awesome-pages-plugin==2.9.3
Requires-Dist: mozilla-metric-config-parser==2024.11.1
Requires-Dist: mozilla-schema-generator==0.5.1
Requires-Dist: pandas==2.2.3
Requires-Dist: pathos==0.3.3
Requires-Dist: pip-tools==7.4.1
Requires-Dist: pre-commit==4.0.1
Requires-Dist: pyarrow==18.1.0
Requires-Dist: pytest-black==0.6.0
Requires-Dist: pytest-flake8==1.3.0
Requires-Dist: pytest-isort==4.0.0
Requires-Dist: pytest-mypy==0.10.3
Requires-Dist: pytest-pydocstyle==2.4.0
Requires-Dist: pytest-xdist==3.6.1
Requires-Dist: pytest==7.4.3
Requires-Dist: PyYAML==6.0.2
Requires-Dist: rich-click==1.8.5
Requires-Dist: smart_open==6.4.0
Requires-Dist: sqlglot==25.28.0
Requires-Dist: sqlparse==0.5.3
Requires-Dist: stripe==6.4.0
Requires-Dist: symbolic==12.13.2
Requires-Dist: siggen==2.2.20241029
Requires-Dist: tomli==2.2.1
Requires-Dist: types-python-dateutil==2.9.0.20241206
Requires-Dist: types-pytz==2024.2.0.20241221
Requires-Dist: types-PyYAML==6.0.12.20241230
Requires-Dist: types-requests==2.32.0.20241016
Requires-Dist: types-ujson==5.10.0.20240515
Requires-Dist: typing==3.7.4.3
Requires-Dist: ujson==5.10.0
Requires-Dist: yamllint==1.35.1
Requires-Dist: requests==2.32.3
Requires-Dist: responses==0.25.6
